[
  {
    "name": "Kosovo",
    "flag": "https://flagcdn.com/xk.svg",
    "capital": "Pristina",
    "population": 1800000,
    "currency": "Euro (€)",
    "idh": 0.750,
    "organizations": ["UNESCO"],
    "headofstate": "A compléter"
  },
  {
    "name": "Bulgarie",
    "flag": "https://flagcdn.com/bg.svg",
    "capital": "Sofia",
    "population": 6700000,
    "currency": "Lev Bulgare (BGN)",
    "idh": 0.816,
    "organizations": ["ONU", "UE", "OTAN", "UNESCO"],
    "headofstate": "A compléter"
  },
  {
    "name": "Roumanie",
    "flag": "https://flagcdn.com/ro.svg",
    "capital": "Bucharest",
    "population": 19000000,
    "currency": "Leu Roumain (RON)",
    "idh": 0.828,
    "organizations": ["ONU", "UE", "OTAN", "UNESCO"],
    "headofstate": "A compléter"
  },
  {
    "name": "Moldavie",
    "flag": "https://flagcdn.com/md.svg",
    "capital": "Chișinău",
    "population": 2600000,
    "currency": "Leu Moldave (MDL)",
    "idh": 0.767,
    "organizations": ["ONU", "UNESCO"],
    "headofstate": "A compléter"
  },
  {
    "name": "Ukraine",
    "flag": "https://flagcdn.com/ua.svg",
    "capital": "Kyiv",
    "population": 37000000,
    "currency": "Hryvnia Ukrainien (UAH)",
    "idh": 0.773,
    "organizations": ["ONU", "UNESCO"],
    "headofstate": "A compléter"
  },
  {
    "name": "Russie",
    "flag": "https://flagcdn.com/ru.svg",
    "capital": "Moscou",
    "population": 143000000,
    "currency": "Rouble Russe (RUB)",
    "idh": 0.822,
    "organizations": ["ONU", "UNESCO"],
    "headofstate": "A compléter"
  },
  {
    "name": "Biélorussie",
    "flag": "https://flagcdn.com/by.svg",
    "capital": "Minsk",
    "population": 9400000,
    "currency": "Rouble Biélorusse (BYN)",
    "idh": 0.808,
    "organizations": ["ONU", "UNESCO"],
    "headofstate": "A compléter"
  },
  {
    "name": "Liechtenstein",
    "flag": "https://flagcdn.com/li.svg",
    "capital": "Vaduz",
    "population": 39000,
    "currency": "Franc Suisse (CHF)",
    "idh": 0.916,
    "organizations": ["ONU", "UNESCO"],
    "headofstate": "A compléter"
  },
  {
    "name": "Luxembourg",
    "flag": "https://flagcdn.com/lu.svg",
    "capital": "Luxembourg",
    "population": 660000,
    "currency": "Euro (€)",
    "idh": 0.930,
    "organizations": ["ONU", "UE", "OTAN", "UNESCO"],
    "headofstate": "A compléter"
  },
  {
    "name": "Andorre",
    "flag": "https://flagcdn.com/ad.svg",
    "capital": "Andorre la Vieille",
    "population": 79000,
    "currency": "Euro (€)",
    "idh": 0.858,
    "organizations": ["ONU", "UNESCO"],
    "headofstate": "A compléter"
  }
]
